{
  "strategy": "DummyStrategy",
  "timestamp": "2025-07-27T20:04:25.572425",
  "metrics": {
    "total_return": -9585960.298217846,
    "roi": -1.0,
    "annualized_return": -1.0,
    "sharpe_ratio": -9023.42537685156,
    "sortino_ratio": -9023.42537685156,
    "calmar_ratio": -0.10431923030037091,
    "max_drawdown": 9.585960298217849,
    "max_drawdown_duration": 0,
    "volatility": 0.1338572600903905,
    "downside_deviation": 0.0,
    "var_95": 0.0,
    "cvar_95": 0.0,
    "total_trades": 32,
    "winning_trades": 0,
    "losing_trades": 17,
    "win_rate": 0.0,
    "profit_factor": 0.0,
    "expectancy": -299561.2593193077,
    "avg_win": 0,
    "avg_loss": 563880.0175422264,
    "avg_win_loss_ratio": 0.0,
    "consistency_score": 0.4042708944077583,
    "max_consecutive_wins": 0,
    "max_consecutive_losses": 32,
    "avg_holding_time_hours": 0.6458333333333334,
    "avg_trades_per_day": 32.0,
    "total_commission": -66.04460351200726,
    "total_slippage": -16928933.32225808,
    "sample_size": 32,
    "confidence_level": 0,
    "composite_score": 0.06064063416116375,
    "weighted_score": 0.031186611854312783
  },
  "trades": [
    {
      "timestamp": "2025-07-24T07:25:00",
      "strategy": "DummyStrategy",
      "signal_action": "SELL",
      "entry_price": 118134.83,
      "exit_price": null,
      "quantity": 0.10242533891147938,
      "pnl": 0,
      "pnl_pct": 0,
      "holding_time": 0,
      "commission": -162.6251724267768,
      "slippage": -5412251.740103563,
      "market_impact": 0.013868650007904822,
      "signal_confidence": 0.3666666666666667,
      "position_size": 0.33,
      "regime": "neutral",
      "volatility": 0.0013745996162960465,
      "sentiment_score": 0.4824723661881079
    },
    {
      "timestamp": "2025-07-24T09:00:00",
      "strategy": "DummyStrategy",
      "signal_action": "BUY",
      "entry_price": 118814.46,
      "exit_price": 5551742.020446887,
      "quantity": 0.12568616087076717,
      "pnl": -1110722.9660826295,
      "pnl_pct": 2.048987157721984,
      "holding_time": 5700.0,
      "commission": 209.33314220846563,
      "slippage": 5431283.454581035,
      "market_impact": 0.013837590692679558,
      "signal_confidence": 0.4666666666666666,
      "position_size": 0.32,
      "regime": "neutral",
      "volatility": 0.0009454824108699442,
      "sentiment_score": 0.883212147598345
    },
    {
      "timestamp": "2025-07-24T09:15:00",
      "strategy": "DummyStrategy",
      "signal_action": "SELL",
      "entry_price": 118563.29,
      "exit_price": -2988331.708321196,
      "quantity": 0.09587003419580098,
      "pnl": -1073369.080522158,
      "pnl_pct": -1.5382691950229799,
      "holding_time": 900.0,
      "commission": -85.94743891954484,
      "slippage": -3107838.480857152,
      "market_impact": 0.00795762782861281,
      "signal_confidence": 0.3666666666666667,
      "position_size": 0.31,
      "regime": "neutral",
      "volatility": 0.0009365842188704737,
      "sentiment_score": 0.7100681587075692
    },
    {
      "timestamp": "2025-07-24T10:35:00",
      "strategy": "DummyStrategy",
      "signal_action": "BUY",
      "entry_price": 118065.99,
      "exit_price": 1860687.1982846335,
      "quantity": 0.09316823583150408,
      "pnl": -464875.60839238635,
      "pnl_pct": 1.6226508232347279,
      "holding_time": 4800.0,
      "commission": 52.007083109533006,
      "slippage": 1742090.2521034537,
      "market_impact": 0.0044971137003951885,
      "signal_confidence": 0.3666666666666667,
      "position_size": 0.3,
      "regime": "neutral",
      "volatility": 0.0010079002534733002,
      "sentiment_score": 0.6267482120459962
    },
    {
      "timestamp": "2025-07-24T14:45:00",
      "strategy": "DummyStrategy",
      "signal_action": "SELL",
      "entry_price": 118809.66,
      "exit_price": -1340580.0355561045,
      "quantity": 0.0894988954040718,
      "pnl": -298256.4206021406,
      "pnl_pct": -1.7204757665834347,
      "holding_time": 15000.0,
      "commission": -35.9941297149068,
      "slippage": -1459835.268998935,
      "market_impact": 0.0037503132559295396,
      "signal_confidence": 0.3666666666666667,
      "position_size": 0.29,
      "regime": "neutral",
      "volatility": 0.0013916657234570764,
      "sentiment_score": 0.6952581420620767
    },
    {
      "timestamp": "2025-07-24T14:50:00",
      "strategy": "DummyStrategy",
      "signal_action": "SELL",
      "entry_price": 118874.38,
      "exit_price": null,
      "quantity": 0.07402772573871678,
      "pnl": 0,
      "pnl_pct": 0,
      "holding_time": 0,
      "commission": -21.717321512341908,
      "slippage": -1097101.4533458222,
      "market_impact": 0.002824294093836266,
      "signal_confidence": 0.3666666666666667,
      "position_size": 0.24,
      "regime": "neutral",
      "volatility": 0.0013954404868016333,
      "sentiment_score": 0.6952581420620767
    },
    {
      "timestamp": "2025-07-24T15:35:00",
      "strategy": "DummyStrategy",
      "signal_action": "SELL",
      "entry_price": 118753.37,
      "exit_price": null,
      "quantity": 0.07410316018821192,
      "pnl": 0,
      "pnl_pct": 0,
      "holding_time": 0,
      "commission": -28.800065766806608,
      "slippage": -1414679.545054585,
      "market_impact": 0.0036370135770452104,
      "signal_confidence": 0.3666666666666667,
      "position_size": 0.24,
      "regime": "neutral",
      "volatility": 0.0016023245438968946,
      "sentiment_score": 0.9023942210103773
    },
    {
      "timestamp": "2025-07-24T18:05:00",
      "strategy": "DummyStrategy",
      "signal_action": "BUY",
      "entry_price": 119331.31,
      "exit_price": 4827055.323441652,
      "quantity": 0.12201324195636504,
      "pnl": -453700.27309304645,
      "pnl_pct": 4.726033719158622,
      "holding_time": 9000.0,
      "commission": 176.68940073475386,
      "slippage": 4706298.422127833,
      "market_impact": 0.011946498482414815,
      "signal_confidence": 0.4666666666666666,
      "position_size": 0.31200000000000006,
      "regime": "neutral",
      "volatility": 0.0010889083907774729,
      "sentiment_score": 0.6249971692715958
    },
    {
      "timestamp": "2025-07-24T19:50:00",
      "strategy": "DummyStrategy",
      "signal_action": "SELL",
      "entry_price": 119090.06,
      "exit_price": -1517826.3460962682,
      "quantity": 0.05418868151828402,
      "pnl": -774159.5823298355,
      "pnl_pct": -1.3144414647011067,
      "holding_time": 6300.0,
      "commission": -24.674702540601427,
      "slippage": -1637415.7050754172,
      "market_impact": 0.004192616740212473,
      "signal_confidence": 0.3666666666666667,
      "position_size": 0.17600000000000002,
      "regime": "neutral",
      "volatility": 0.0006716141843481535,
      "sentiment_score": 0.8074182439290737
    },
    {
      "timestamp": "2025-07-24T19:55:00",
      "strategy": "DummyStrategy",
      "signal_action": "BUY",
      "entry_price": 118943.42,
      "exit_price": 2998356.881831658,
      "quantity": 0.06165396398836804,
      "pnl": -244726.01461640227,
      "pnl_pct": 2.9754281440318913,
      "holding_time": 300.0,
      "commission": 55.45817616501736,
      "slippage": 2878539.1883417256,
      "market_impact": 0.0073503308542189,
      "signal_confidence": 0.3666666666666667,
      "position_size": 0.2,
      "regime": "neutral",
      "volatility": 0.0007093152914499246,
      "sentiment_score": 0.8074182439290737
    },
    {
      "timestamp": "2025-07-24T21:40:00",
      "strategy": "DummyStrategy",
      "signal_action": "SELL",
      "entry_price": 118605.95,
      "exit_price": -2957589.880615145,
      "quantity": 0.05193668614432919,
      "pnl": -367207.7272085324,
      "pnl_pct": -1.9864035527379886,
      "holding_time": 6300.0,
      "commission": -46.082225211945854,
      "slippage": -3077130.045392087,
      "market_impact": 0.007876626568415795,
      "signal_confidence": 0.3666666666666667,
      "position_size": 0.168,
      "regime": "neutral",
      "volatility": 0.0005078009293989079,
      "sentiment_score": 0.9159286364769724
    },
    {
      "timestamp": "2025-07-24T21:45:00",
      "strategy": "DummyStrategy",
      "signal_action": "SELL",
      "entry_price": 118561.71,
      "exit_price": null,
      "quantity": 0.06185245922425828,
      "pnl": 0,
      "pnl_pct": 0,
      "holding_time": 0,
      "commission": -178.18759272533256,
      "slippage": -9724328.573460942,
      "market_impact": 0.0247719302964641,
      "signal_confidence": 0.3666666666666667,
      "position_size": 0.2,
      "regime": "neutral",
      "volatility": 0.0005084941037053753,
      "sentiment_score": 0.9159286364769724
    },
    {
      "timestamp": "2025-07-24T23:10:00",
      "strategy": "DummyStrategy",
      "signal_action": "SELL",
      "entry_price": 118336.27,
      "exit_price": null,
      "quantity": 0.06940672824429345,
      "pnl": 0,
      "pnl_pct": 0,
      "holding_time": 0,
      "commission": -27.388415917049095,
      "slippage": -1434132.4177010027,
      "market_impact": 0.00369958500909679,
      "signal_confidence": 0.3666666666666667,
      "position_size": 0.22400000000000003,
      "regime": "neutral",
      "volatility": 0.000595518058815508,
      "sentiment_score": 0.6141671649014356
    },
    {
      "timestamp": "2025-07-24T23:55:00",
      "strategy": "DummyStrategy",
      "signal_action": "SELL",
      "entry_price": 118340.99,
      "exit_price": null,
      "quantity": 0.06692524711851744,
      "pnl": 0,
      "pnl_pct": 0,
      "holding_time": 0,
      "commission": -147.64326657646762,
      "slippage": -7474241.2473302875,
      "market_impact": 0.019093507504648336,
      "signal_confidence": 0.3666666666666667,
      "position_size": 0.21600000000000003,
      "regime": "neutral",
      "volatility": 0.0005894042146280685,
      "sentiment_score": 0.6141671649014356
    },
    {
      "timestamp": "2025-07-25T00:50:00",
      "strategy": "DummyStrategy",
      "signal_action": "BUY",
      "entry_price": 117672.58,
      "exit_price": 2750494.243480578,
      "quantity": 0.1701330930281294,
      "pnl": -676221.7288645561,
      "pnl_pct": 1.3740316328906061,
      "holding_time": 3300.0,
      "commission": 140.38502789982468,
      "slippage": 2632021.81476555,
      "market_impact": 0.006797239552560023,
      "signal_confidence": 0.4666666666666666,
      "position_size": 0.42900000000000005,
      "regime": "neutral",
      "volatility": 0.0006889951159943627,
      "sentiment_score": 0.5874349406978615
    },
    {
      "timestamp": "2025-07-25T01:15:00",
      "strategy": "DummyStrategy",
      "signal_action": "SELL",
      "entry_price": 117475.82,
      "exit_price": -262360.8292141168,
      "quantity": 0.1398301937085152,
      "pnl": -512586.35236303805,
      "pnl_pct": -1.0953867945137437,
      "holding_time": 1500.0,
      "commission": -11.005789671160988,
      "slippage": -379954.5154135096,
      "market_impact": 0.0010033230616549788,
      "signal_confidence": 0.4666666666666666,
      "position_size": 0.35200000000000004,
      "regime": "neutral",
      "volatility": 0.0005646153734356331,
      "sentiment_score": 0.6484405498280913
    },
    {
      "timestamp": "2025-07-25T02:15:00",
      "strategy": "DummyStrategy",
      "signal_action": "SELL",
      "entry_price": 117181.0,
      "exit_price": null,
      "quantity": 0.16208543478322707,
      "pnl": 0,
      "pnl_pct": 0,
      "holding_time": 0,
      "commission": -85.0842808618116,
      "slippage": -1867532.459890315,
      "market_impact": 0.004854748705123241,
      "signal_confidence": 0.4666666666666666,
      "position_size": 0.40700000000000003,
      "regime": "neutral",
      "volatility": 0.0006256008199149597,
      "sentiment_score": 0.7656347589290746
    },
    {
      "timestamp": "2025-07-25T03:25:00",
      "strategy": "DummyStrategy",
      "signal_action": "SELL",
      "entry_price": 116024.05,
      "exit_price": null,
      "quantity": 0.15927732224482768,
      "pnl": 0,
      "pnl_pct": 0,
      "holding_time": 0,
      "commission": -41.48383841687861,
      "slippage": -984493.5740606476,
      "market_impact": 0.002599505087907037,
      "signal_confidence": 0.4666666666666666,
      "position_size": 0.396,
      "regime": "neutral",
      "volatility": 0.0014078063125592451,
      "sentiment_score": 0.5263969196797375
    },
    {
      "timestamp": "2025-07-25T06:45:00",
      "strategy": "DummyStrategy",
      "signal_action": "SELL",
      "entry_price": 115377.32,
      "exit_price": null,
      "quantity": 0.09788174429197469,
      "pnl": 0,
      "pnl_pct": 0,
      "holding_time": 0,
      "commission": -8.682642674554016,
      "slippage": -411189.49637895124,
      "market_impact": 0.0011041521484919422,
      "signal_confidence": 0.3666666666666667,
      "position_size": 0.30800000000000005,
      "regime": "neutral",
      "volatility": 0.0012096160959602798,
      "sentiment_score": 0.4742838012438908
    },
    {
      "timestamp": "2025-07-25T07:30:00",
      "strategy": "DummyStrategy",
      "signal_action": "SELL",
      "entry_price": 115300.0,
      "exit_price": null,
      "quantity": 0.1154379878577624,
      "pnl": 0,
      "pnl_pct": 0,
      "holding_time": 0,
      "commission": -22.823594790077433,
      "slippage": -774581.3683228832,
      "market_impact": 0.002063507967532708,
      "signal_confidence": 0.3666666666666667,
      "position_size": 0.36300000000000004,
      "regime": "neutral",
      "volatility": 0.0013525432183533659,
      "sentiment_score": 0.3319083572576337
    },
    {
      "timestamp": "2025-07-25T08:05:00",
      "strategy": "DummyStrategy",
      "signal_action": "BUY",
      "entry_price": 115476.86,
      "exit_price": 729722.3607893917,
      "quantity": 0.0825562223750571,
      "pnl": -160316.33032460161,
      "pnl_pct": 2.1072446974168053,
      "holding_time": 2100.0,
      "commission": 18.0729364468142,
      "slippage": 614056.346110211,
      "market_impact": 0.0016380310235379395,
      "signal_confidence": 0.3666666666666667,
      "position_size": 0.26,
      "regime": "neutral",
      "volatility": 0.001956292287097304,
      "sentiment_score": 0.3319083572576337
    },
    {
      "timestamp": "2025-07-25T09:30:00",
      "strategy": "DummyStrategy",
      "signal_action": "BUY",
      "entry_price": 115828.2,
      "exit_price": null,
      "quantity": 0.09496823744131397,
      "pnl": 0,
      "pnl_pct": 0,
      "holding_time": 0,
      "commission": 45.694130188058374,
      "slippage": 1487556.8829185301,
      "market_impact": 0.003919275369094406,
      "signal_confidence": 0.3666666666666667,
      "position_size": 0.3,
      "regime": "neutral",
      "volatility": 0.001778530053770892,
      "sentiment_score": 0.3470706189660148
    },
    {
      "timestamp": "2025-07-25T10:20:00",
      "strategy": "DummyStrategy",
      "signal_action": "BUY",
      "entry_price": 116246.05,
      "exit_price": null,
      "quantity": 0.16459340625624125,
      "pnl": 0,
      "pnl_pct": 0,
      "holding_time": 0,
      "commission": 210.5612944229513,
      "slippage": 4146768.6194588454,
      "market_impact": 0.01081233675688804,
      "signal_confidence": 0.4666666666666666,
      "position_size": 0.41,
      "regime": "neutral",
      "volatility": 0.0014676928637043128,
      "sentiment_score": 0.3528191225419707
    },
    {
      "timestamp": "2025-07-25T11:55:00",
      "strategy": "DummyStrategy",
      "signal_action": "BUY",
      "entry_price": 116543.58,
      "exit_price": null,
      "quantity": 0.0912391170181432,
      "pnl": 0,
      "pnl_pct": 0,
      "holding_time": 0,
      "commission": 35.4417583891983,
      "slippage": 1177926.7303740855,
      "market_impact": 0.0030908939743859777,
      "signal_confidence": 0.3666666666666667,
      "position_size": 0.29,
      "regime": "neutral",
      "volatility": 0.0009603478224486173,
      "sentiment_score": 0.5216606199887803
    },
    {
      "timestamp": "2025-07-25T12:00:00",
      "strategy": "DummyStrategy",
      "signal_action": "SELL",
      "entry_price": 116548.4,
      "exit_price": -1912904.811721398,
      "quantity": 0.1006734827190535,
      "pnl": -292670.9405918788,
      "pnl_pct": -2.4773398998262777,
      "holding_time": 300.0,
      "commission": -57.77363685180855,
      "slippage": -2030071.2260354918,
      "market_impact": 0.005302640912221147,
      "signal_confidence": 0.3666666666666667,
      "position_size": 0.32,
      "regime": "neutral",
      "volatility": 0.0009605453978621949,
      "sentiment_score": 0.5216606199887803
    },
    {
      "timestamp": "2025-07-25T12:10:00",
      "strategy": "DummyStrategy",
      "signal_action": "BUY",
      "entry_price": 116519.54,
      "exit_price": 898423.8206276451,
      "quantity": 0.07552381343077737,
      "pnl": -283026.2444863717,
      "pnl_pct": 1.4696646770516328,
      "holding_time": 600.0,
      "commission": 20.35571790325454,
      "slippage": 781664.2081073185,
      "market_impact": 0.002060362753977601,
      "signal_confidence": 0.3666666666666667,
      "position_size": 0.24,
      "regime": "neutral",
      "volatility": 0.0008332000001981638,
      "sentiment_score": 0.3063448123220084
    },
    {
      "timestamp": "2025-07-25T16:40:00",
      "strategy": "DummyStrategy",
      "signal_action": "BUY",
      "entry_price": 115913.74,
      "exit_price": null,
      "quantity": 0.06832667119532164,
      "pnl": 0,
      "pnl_pct": 0,
      "holding_time": 0,
      "commission": 41.63992303844786,
      "slippage": 1914916.861267653,
      "market_impact": 0.005031403444515184,
      "signal_confidence": 0.3666666666666667,
      "position_size": 0.21600000000000003,
      "regime": "neutral",
      "volatility": 0.0011857584100582472,
      "sentiment_score": 0.3089515028559528
    },
    {
      "timestamp": "2025-07-25T19:20:00",
      "strategy": "DummyStrategy",
      "signal_action": "SELL",
      "entry_price": 116621.27,
      "exit_price": -6915762.4093059935,
      "quantity": 0.11844608906534229,
      "pnl": -611330.7676671088,
      "pnl_pct": -4.404408483915606,
      "holding_time": 9600.0,
      "commission": -245.7435030862212,
      "slippage": -7034510.788675471,
      "market_impact": 0.018239463259815,
      "signal_confidence": 0.4666666666666666,
      "position_size": 0.296,
      "regime": "neutral",
      "volatility": 0.0005823049545080054,
      "sentiment_score": 0.2432881553795128
    },
    {
      "timestamp": "2025-07-25T20:30:00",
      "strategy": "DummyStrategy",
      "signal_action": "BUY",
      "entry_price": 116931.88,
      "exit_price": 2011812.7267918666,
      "quantity": 0.08027465791764117,
      "pnl": -1057436.3597077825,
      "pnl_pct": 1.290902522053784,
      "holding_time": 4200.0,
      "commission": 48.4492735312722,
      "slippage": 1894303.8692919,
      "market_impact": 0.004934304485367232,
      "signal_confidence": 0.3666666666666667,
      "position_size": 0.256,
      "regime": "neutral",
      "volatility": 0.0009808076743032979,
      "sentiment_score": 0.2834928904679644
    },
    {
      "timestamp": "2025-07-25T22:40:00",
      "strategy": "DummyStrategy",
      "signal_action": "BUY",
      "entry_price": 117340.15,
      "exit_price": null,
      "quantity": 0.06749607870792736,
      "pnl": 0,
      "pnl_pct": 0,
      "holding_time": 0,
      "commission": 80.11747918473617,
      "slippage": 3838144.614079396,
      "market_impact": 0.009918306162900075,
      "signal_confidence": 0.3666666666666667,
      "position_size": 0.21600000000000003,
      "regime": "neutral",
      "volatility": 0.0005299606408664803,
      "sentiment_score": 0.4156203278742474
    },
    {
      "timestamp": "2025-07-25T22:55:00",
      "strategy": "DummyStrategy",
      "signal_action": "SELL",
      "entry_price": 117279.97,
      "exit_price": -4952143.769018063,
      "quantity": 0.06502957552484596,
      "pnl": -601308.5495557358,
      "pnl_pct": -2.251600608286348,
      "holding_time": 900.0,
      "commission": -96.61074217117665,
      "slippage": -5070959.250545529,
      "market_impact": 0.01309270054780893,
      "signal_confidence": 0.3666666666666667,
      "position_size": 0.20800000000000002,
      "regime": "neutral",
      "volatility": 0.0004969586691908099,
      "sentiment_score": 0.4156203278742474
    },
    {
      "timestamp": "2025-07-25T23:55:00",
      "strategy": "DummyStrategy",
      "signal_action": "BUY",
      "entry_price": 117614.31,
      "exit_price": 4336635.1740161525,
      "quantity": 0.09840072465105082,
      "pnl": -604045.3518096425,
      "pnl_pct": 1.875708657964921,
      "holding_time": 3600.0,
      "commission": 128.01841310112758,
      "slippage": 4217742.570856975,
      "market_impact": 0.010868517267818468,
      "signal_confidence": 0.4666666666666666,
      "position_size": 0.248,
      "regime": "neutral",
      "volatility": 0.0005605054829664116,
      "sentiment_score": 0.1706526113973584
    }
  ],
  "summary": {
    "total_trades": 32,
    "roi": "-100.00%",
    "sharpe_ratio": "-9023.43",
    "win_rate": "0.00%",
    "max_drawdown": "958.60%",
    "composite_score": "0.061"
  }
}