{
  "strategy": "SimpleMA",
  "timestamp": "2025-07-27T23:04:56.534469",
  "metrics": {
    "total_return": -1249.8165081836755,
    "roi": -0.0012498165081836754,
    "annualized_return": -0.0012498165081836754,
    "sharpe_ratio": -20.6266447079151,
    "sortino_ratio": -20.6266447079151,
    "calmar_ratio": -0.9823608398396629,
    "max_drawdown": 0.0012722580720824189,
    "max_drawdown_duration": 0,
    "volatility": 0.00860425350532361,
    "downside_deviation": 0.0,
    "var_95": 0.0,
    "cvar_95": 0.0,
    "total_trades": 29,
    "winning_trades": 8,
    "losing_trades": 10,
    "win_rate": 0.27586206896551724,
    "profit_factor": 0.17337918283441733,
    "expectancy": -43.09712097185088,
    "avg_win": 32.7677697533784,
    "avg_loss": 151.19586662107028,
    "avg_win_loss_ratio": 0.21672397854302167,
    "consistency_score": 0,
    "max_consecutive_wins": 4,
    "max_consecutive_losses": 7,
    "avg_holding_time_hours": 0.9655172413793104,
    "avg_trades_per_day": 29.0,
    "total_commission": 97.11779743724956,
    "total_slippage": 204.93005124736592,
    "sample_size": 29,
    "confidence_level": 0.1469858133850274,
    "composite_score": 0.33724983283900234,
    "weighted_score": 0.16300408587218446
  },
  "trades": [
    {
      "timestamp": "2025-07-24T10:45:00",
      "strategy": "SimpleMA",
      "signal_action": "SELL",
      "entry_price": 118292.96,
      "exit_price": null,
      "quantity": 0.0960891220125582,
      "pnl": 0,
      "pnl_pct": 0,
      "holding_time": 0,
      "commission": 3.424065850592422,
      "slippage": -77.97422874636071,
      "market_impact": 0.0047840449109602294,
      "signal_confidence": 0.3666666666666667,
      "position_size": 0.31,
      "regime": "neutral",
      "volatility": 0.0010853209506963798,
      "sentiment_score": 0.5
    },
    {
      "timestamp": "2025-07-24T11:40:00",
      "strategy": "SimpleMA",
      "signal_action": "BUY",
      "entry_price": 118640.0,
      "exit_price": 121193.28680743201,
      "quantity": 0.14160485502360082,
      "pnl": -231.8036878342243,
      "pnl_pct": -0.02030951196170351,
      "holding_time": 3300.0,
      "commission": 5.148467342460026,
      "slippage": 151.95583266590955,
      "market_impact": 0.020240483603895035,
      "signal_confidence": 0.4666666666666666,
      "position_size": 0.36,
      "regime": "neutral",
      "volatility": 0.0009749422859133417,
      "sentiment_score": 0.5
    },
    {
      "timestamp": "2025-07-24T13:40:00",
      "strategy": "SimpleMA",
      "signal_action": "BUY",
      "entry_price": 118614.94,
      "exit_price": null,
      "quantity": 0.08037211276533408,
      "pnl": 0,
      "pnl_pct": 0,
      "holding_time": 0,
      "commission": 2.894178006582024,
      "slippage": 107.97172244619065,
      "market_impact": 0.011040081100157006,
      "signal_confidence": 0.3666666666666667,
      "position_size": 0.26,
      "regime": "neutral",
      "volatility": 0.0007507360827346823,
      "sentiment_score": 0.5
    },
    {
      "timestamp": "2025-07-24T15:10:00",
      "strategy": "SimpleMA",
      "signal_action": "SELL",
      "entry_price": 119265.53,
      "exit_price": 119438.20538375725,
      "quantity": 0.09530554776947428,
      "pnl": -47.759110347609585,
      "pnl_pct": -0.004950536239201019,
      "holding_time": 5400.0,
      "commission": 3.414937076610587,
      "slippage": -64.55705461906201,
      "market_impact": 0.0019891115092207285,
      "signal_confidence": 0.3666666666666667,
      "position_size": 0.31,
      "regime": "neutral",
      "volatility": 0.001548292087899097,
      "sentiment_score": 0.5
    },
    {
      "timestamp": "2025-07-24T15:35:00",
      "strategy": "SimpleMA",
      "signal_action": "BUY",
      "entry_price": 118753.37,
      "exit_price": 119313.65603796914,
      "quantity": 0.08336605521173843,
      "pnl": 11.870243624665425,
      "pnl_pct": 0.0010427931781788742,
      "holding_time": 1500.0,
      "commission": 2.984012651032711,
      "slippage": 74.87394885162614,
      "market_impact": 0.004087564749678322,
      "signal_confidence": 0.3666666666666667,
      "position_size": 0.27,
      "regime": "neutral",
      "volatility": 0.0016023245438968946,
      "sentiment_score": 0.5
    },
    {
      "timestamp": "2025-07-24T17:55:00",
      "strategy": "SimpleMA",
      "signal_action": "SELL",
      "entry_price": 119122.94,
      "exit_price": 120487.16276973681,
      "quantity": 0.12222666767626791,
      "pnl": 97.83062699189055,
      "pnl_pct": 0.009835477100745522,
      "holding_time": 8400.0,
      "commission": 4.418023320933907,
      "slippage": -101.556533929165,
      "market_impact": 0.012304760977742635,
      "signal_confidence": 0.4666666666666666,
      "position_size": 0.31200000000000006,
      "regime": "neutral",
      "volatility": 0.0010891387932132912,
      "sentiment_score": 0.5
    },
    {
      "timestamp": "2025-07-24T18:30:00",
      "strategy": "SimpleMA",
      "signal_action": "BUY",
      "entry_price": 119150.99,
      "exit_price": 119913.12399477212,
      "quantity": 0.06400842046437608,
      "pnl": 70.16284658090119,
      "pnl_pct": 0.004764314818017061,
      "holding_time": 2100.0,
      "commission": 2.3026348979562714,
      "slippage": 73.87176926467421,
      "market_impact": 0.005776386965038566,
      "signal_confidence": 0.3666666666666667,
      "position_size": 0.20800000000000002,
      "regime": "neutral",
      "volatility": 0.0010141544297609477,
      "sentiment_score": 0.5
    },
    {
      "timestamp": "2025-07-24T18:50:00",
      "strategy": "SimpleMA",
      "signal_action": "SELL",
      "entry_price": 119101.98,
      "exit_price": 120292.60662734375,
      "quantity": 0.07881201191337599,
      "pnl": 24.290083904573077,
      "pnl_pct": 0.0031646463700518053,
      "holding_time": 1200.0,
      "commission": 2.84415070398158,
      "slippage": -95.14023054300723,
      "market_impact": 0.010795512029999522,
      "signal_confidence": 0.3666666666666667,
      "position_size": 0.256,
      "regime": "neutral",
      "volatility": 0.0009367168141758674,
      "sentiment_score": 0.5
    },
    {
      "timestamp": "2025-07-24T19:15:00",
      "strategy": "SimpleMA",
      "signal_action": "SELL",
      "entry_price": 119310.74,
      "exit_price": null,
      "quantity": 0.07867411321618378,
      "pnl": 0,
      "pnl_pct": 0,
      "holding_time": 0,
      "commission": 2.8395131907117257,
      "slippage": -87.97751054413439,
      "market_impact": 0.009087235972739187,
      "signal_confidence": 0.3666666666666667,
      "position_size": 0.256,
      "regime": "neutral",
      "volatility": 0.0008532453913539054,
      "sentiment_score": 0.5
    },
    {
      "timestamp": "2025-07-24T19:35:00",
      "strategy": "SimpleMA",
      "signal_action": "BUY",
      "entry_price": 119041.09,
      "exit_price": 120053.00966388211,
      "quantity": 0.06406751371872241,
      "pnl": 19.97989479921829,
      "pnl_pct": 0.002110914102942799,
      "holding_time": 1200.0,
      "commission": 2.3074493530844045,
      "slippage": 82.43859154068728,
      "market_impact": 0.007808069233416999,
      "signal_confidence": 0.3666666666666667,
      "position_size": 0.20800000000000002,
      "regime": "neutral",
      "volatility": 0.0008100581505251622,
      "sentiment_score": 0.5
    },
    {
      "timestamp": "2025-07-24T20:30:00",
      "strategy": "SimpleMA",
      "signal_action": "BUY",
      "entry_price": 118852.15,
      "exit_price": null,
      "quantity": 0.06663741463658841,
      "pnl": 0,
      "pnl_pct": 0,
      "holding_time": 0,
      "commission": 2.3958868322476117,
      "slippage": 81.82262744345745,
      "market_impact": 0.0076814384436572755,
      "signal_confidence": 0.3666666666666667,
      "position_size": 0.21600000000000003,
      "regime": "neutral",
      "volatility": 0.0006901312542263344,
      "sentiment_score": 0.5
    },
    {
      "timestamp": "2025-07-24T21:00:00",
      "strategy": "SimpleMA",
      "signal_action": "BUY",
      "entry_price": 118768.07,
      "exit_price": null,
      "quantity": 0.07409398839267153,
      "pnl": 0,
      "pnl_pct": 0,
      "holding_time": 0,
      "commission": 2.6976910356483605,
      "slippage": 137.07293935572633,
      "market_impact": 0.02069854220268488,
      "signal_confidence": 0.3666666666666667,
      "position_size": 0.24,
      "regime": "neutral",
      "volatility": 0.0005696571258743562,
      "sentiment_score": 0.5
    },
    {
      "timestamp": "2025-07-24T23:25:00",
      "strategy": "SimpleMA",
      "signal_action": "SELL",
      "entry_price": 118230.12,
      "exit_price": 118850.23878871066,
      "quantity": 0.11367661641551238,
      "pnl": -186.21523888423272,
      "pnl_pct": -0.02070829124872092,
      "holding_time": 8700.0,
      "commission": 4.053147901702895,
      "slippage": -122.91647972528355,
      "market_impact": 0.006284652916159994,
      "signal_confidence": 0.4666666666666666,
      "position_size": 0.288,
      "regime": "neutral",
      "volatility": 0.000629908631717972,
      "sentiment_score": 0.5
    },
    {
      "timestamp": "2025-07-25T01:30:00",
      "strategy": "SimpleMA",
      "signal_action": "BUY",
      "entry_price": 117512.91,
      "exit_price": 118722.93056888324,
      "quantity": 0.16162763166475352,
      "pnl": 14.471967671863414,
      "pnl_pct": 0.0010711650319335604,
      "holding_time": 7500.0,
      "commission": 5.756671827644271,
      "slippage": 141.76499776347808,
      "market_impact": 0.009090537976804168,
      "signal_confidence": 0.4666666666666666,
      "position_size": 0.40700000000000003,
      "regime": "neutral",
      "volatility": 0.0006296179977137816,
      "sentiment_score": 0.5
    },
    {
      "timestamp": "2025-07-25T03:50:00",
      "strategy": "SimpleMA",
      "signal_action": "SELL",
      "entry_price": 115412.36,
      "exit_price": 115696.50096351467,
      "quantity": 0.18680841462734146,
      "pnl": -489.15464951581635,
      "pnl_pct": -0.025491533866851684,
      "holding_time": 8400.0,
      "commission": 6.483923976877458,
      "slippage": -99.20860873914663,
      "market_impact": 0.0033215642783304953,
      "signal_confidence": 0.4666666666666666,
      "position_size": 0.462,
      "regime": "neutral",
      "volatility": 0.0017577553579351426,
      "sentiment_score": 0.5
    },
    {
      "timestamp": "2025-07-25T05:25:00",
      "strategy": "SimpleMA",
      "signal_action": "BUY",
      "entry_price": 115611.37,
      "exit_price": 116147.47544907265,
      "quantity": 0.09768358711892557,
      "pnl": -84.24582868446667,
      "pnl_pct": -0.003897909459683608,
      "holding_time": 5700.0,
      "commission": 3.403710611001827,
      "slippage": 103.63673338091533,
      "market_impact": 0.0037407109325989507,
      "signal_confidence": 0.3666666666666667,
      "position_size": 0.30800000000000005,
      "regime": "neutral",
      "volatility": 0.0020046585022948826,
      "sentiment_score": 0.5
    },
    {
      "timestamp": "2025-07-25T06:20:00",
      "strategy": "SimpleMA",
      "signal_action": "BUY",
      "entry_price": 115299.86,
      "exit_price": null,
      "quantity": 0.104943752750437,
      "pnl": 0,
      "pnl_pct": 0,
      "holding_time": 0,
      "commission": 3.638806122717909,
      "slippage": 88.44352067139393,
      "market_impact": 0.0016588551592817645,
      "signal_confidence": 0.3666666666666667,
      "position_size": 0.33,
      "regime": "neutral",
      "volatility": 0.0017462291483821227,
      "sentiment_score": 0.5
    },
    {
      "timestamp": "2025-07-25T07:50:00",
      "strategy": "SimpleMA",
      "signal_action": "SELL",
      "entry_price": 114765.99,
      "exit_price": 114772.34167754794,
      "quantity": 0.09488873837972385,
      "pnl": -84.71349479576025,
      "pnl_pct": -0.006984172165717292,
      "holding_time": 5400.0,
      "commission": 3.267180810800737,
      "slippage": -82.41761579261173,
      "market_impact": 0.0007734808312161619,
      "signal_confidence": 0.3666666666666667,
      "position_size": 0.29700000000000004,
      "regime": "neutral",
      "volatility": 0.0015962280611832552,
      "sentiment_score": 0.5
    },
    {
      "timestamp": "2025-07-25T12:05:00",
      "strategy": "SimpleMA",
      "signal_action": "BUY",
      "entry_price": 116473.5,
      "exit_price": 117316.9250123561,
      "quantity": 0.10073822228518363,
      "pnl": -241.45230234201725,
      "pnl_pct": -0.022170701561157944,
      "holding_time": 15300.0,
      "commission": 3.5454895409126848,
      "slippage": 85.33903206651982,
      "market_impact": 0.0065086563062807384,
      "signal_confidence": 0.3666666666666667,
      "position_size": 0.32,
      "regime": "neutral",
      "volatility": 0.0009310538059216947,
      "sentiment_score": 0.5
    },
    {
      "timestamp": "2025-07-25T12:15:00",
      "strategy": "SimpleMA",
      "signal_action": "BUY",
      "entry_price": 116473.5,
      "exit_price": null,
      "quantity": 0.0818498056067117,
      "pnl": 0,
      "pnl_pct": 0,
      "holding_time": 0,
      "commission": 2.8757061131095063,
      "slippage": 77.32820035140095,
      "market_impact": 0.004827735545280283,
      "signal_confidence": 0.3666666666666667,
      "position_size": 0.26,
      "regime": "neutral",
      "volatility": 0.0008355146261561689,
      "sentiment_score": 0.5
    },
    {
      "timestamp": "2025-07-25T12:30:00",
      "strategy": "SimpleMA",
      "signal_action": "BUY",
      "entry_price": 116033.44,
      "exit_price": null,
      "quantity": 0.09164024899488746,
      "pnl": 0,
      "pnl_pct": 0,
      "holding_time": 0,
      "commission": 3.1951918876177317,
      "slippage": 59.17358880001063,
      "market_impact": 0.0011175808445971452,
      "signal_confidence": 0.3666666666666667,
      "position_size": 0.29,
      "regime": "neutral",
      "volatility": 0.0009977475087998423,
      "sentiment_score": 0.5
    },
    {
      "timestamp": "2025-07-25T14:05:00",
      "strategy": "SimpleMA",
      "signal_action": "SELL",
      "entry_price": 115902.42,
      "exit_price": 116234.23847901056,
      "quantity": 0.08858026145326965,
      "pnl": 1.0949305552179136,
      "pnl_pct": 0.00010280420648234724,
      "holding_time": 5700.0,
      "commission": 3.0888177702877355,
      "slippage": -69.54361128205008,
      "market_impact": 0.003462931061254813,
      "signal_confidence": 0.3666666666666667,
      "position_size": 0.28,
      "regime": "neutral",
      "volatility": 0.001982612779162647,
      "sentiment_score": 0.5
    },
    {
      "timestamp": "2025-07-25T17:10:00",
      "strategy": "SimpleMA",
      "signal_action": "BUY",
      "entry_price": 116280.68,
      "exit_price": 117441.19066146051,
      "quantity": 0.07820158373113517,
      "pnl": -106.91213988301129,
      "pnl_pct": -0.010383792230616314,
      "holding_time": 11100.0,
      "commission": 2.755226131498924,
      "slippage": 87.31451247764687,
      "market_impact": 0.009229359073088274,
      "signal_confidence": 0.3666666666666667,
      "position_size": 0.248,
      "regime": "neutral",
      "volatility": 0.0011963791282254088,
      "sentiment_score": 0.5
    },
    {
      "timestamp": "2025-07-25T19:15:00",
      "strategy": "SimpleMA",
      "signal_action": "SELL",
      "entry_price": 116659.54,
      "exit_price": 117109.99539849853,
      "quantity": 0.11840723299040382,
      "pnl": -25.899994087876397,
      "pnl_pct": -0.002820094560491052,
      "holding_time": 7500.0,
      "commission": 4.160001153196541,
      "slippage": -67.15947913311167,
      "market_impact": 0.0044369699866093956,
      "signal_confidence": 0.4666666666666666,
      "position_size": 0.296,
      "regime": "neutral",
      "volatility": 0.0006554312112645249,
      "sentiment_score": 0.5
    },
    {
      "timestamp": "2025-07-25T20:05:00",
      "strategy": "SimpleMA",
      "signal_action": "SELL",
      "entry_price": 116580.51,
      "exit_price": null,
      "quantity": 0.07045202781608466,
      "pnl": 0,
      "pnl_pct": 0,
      "holding_time": 0,
      "commission": 2.4801629771731855,
      "slippage": -78.99017582195725,
      "market_impact": 0.007237208844337025,
      "signal_confidence": 0.3666666666666667,
      "position_size": 0.22400000000000003,
      "regime": "neutral",
      "volatility": 0.0008951681436075501,
      "sentiment_score": 0.5
    },
    {
      "timestamp": "2025-07-25T20:30:00",
      "strategy": "SimpleMA",
      "signal_action": "BUY",
      "entry_price": 116931.88,
      "exit_price": 117541.14679798749,
      "quantity": 0.0752574917977886,
      "pnl": -13.802219835688053,
      "pnl_pct": -0.0016695136524559455,
      "holding_time": 1500.0,
      "commission": 2.6537555673156628,
      "slippage": 68.0827621580574,
      "market_impact": 0.0046281992201735725,
      "signal_confidence": 0.3666666666666667,
      "position_size": 0.24,
      "regime": "neutral",
      "volatility": 0.0009808076743032979,
      "sentiment_score": 0.5
    },
    {
      "timestamp": "2025-07-25T21:45:00",
      "strategy": "SimpleMA",
      "signal_action": "BUY",
      "entry_price": 117177.59,
      "exit_price": null,
      "quantity": 0.07760300696859641,
      "pnl": 0,
      "pnl_pct": 0,
      "holding_time": 0,
      "commission": 2.745151443985404,
      "slippage": 72.58756286218453,
      "market_impact": 0.005667719956530536,
      "signal_confidence": 0.3666666666666667,
      "position_size": 0.248,
      "regime": "neutral",
      "volatility": 0.0008858482214784149,
      "sentiment_score": 0.5
    },
    {
      "timestamp": "2025-07-25T22:00:00",
      "strategy": "SimpleMA",
      "signal_action": "SELL",
      "entry_price": 117241.88,
      "exit_price": 118203.4915334581,
      "quantity": 0.07005460278642184,
      "pnl": 22.44156389869738,
      "pnl_pct": 0.0024524946280686916,
      "holding_time": 900.0,
      "commission": 2.4842095942033757,
      "slippage": -143.91866808432576,
      "market_impact": 0.00942948203783859,
      "signal_confidence": 0.3666666666666667,
      "position_size": 0.22400000000000003,
      "regime": "neutral",
      "volatility": 0.0008508262902565857,
      "sentiment_score": 0.5
    },
    {
      "timestamp": "2025-07-25T22:05:00",
      "strategy": "SimpleMA",
      "signal_action": "SELL",
      "entry_price": 117231.27,
      "exit_price": null,
      "quantity": 0.08006964922129281,
      "pnl": 0,
      "pnl_pct": 0,
      "holding_time": 0,
      "commission": 2.859633745362095,
      "slippage": -197.38809389229718,
      "market_impact": 0.017178687497734085,
      "signal_confidence": 0.3666666666666667,
      "position_size": 0.256,
      "regime": "neutral",
      "volatility": 0.0008536682063388443,
      "sentiment_score": 0.5
    }
  ],
  "summary": {
    "total_trades": 29,
    "roi": "-0.12%",
    "sharpe_ratio": "-20.63",
    "win_rate": "27.59%",
    "max_drawdown": "0.13%",
    "composite_score": "0.337"
  }
}